{
    "description": "",
    "content": {
        "multipart/form-data": {
            "schema": {
                "allOf": [
                    {
                        "type": "object",
                        "properties": {
                            "cover_image": {
                                "type": "string",
                                "format": "binary"
                            }
                        },
                        "required": ["cover_image"]
                    },
                    {
                        "type": "object",
                        "properties": {
                            "title": {
                                "title": "Post title",
                                "description": "Post title",
                                "type": "string"
                            },
                            "description": {
                                "title": "Post description",
                                "description": "Post description",
                                "type": "string"
                            }
                        },
                        "required": ["title", "description"]
                    },
                    {
                        "type": "object",
                        "properties": {
                            "content": {
                                "title": "Post content",
                                "description": "Post content",
                                "type": "string"
                            }
                        },
                        "required": ["content"]
                    }
                ]
            }
        }
    }
}
